{
    "-d10.jpg": {
        "n1": "B4",
        "n2": "C4",
        "name": "M7"
    },
    "-d10005.jpg": {
        "n1": "E5",
        "n2": "B-4",
        "name": "d5"
    },
    "-d10007.jpg": {
        "n1": "F#5",
        "n2": "B-4",
        "name": "m6"
    },
    "-d10008.jpg": {
        "n1": "G5",
        "n2": "B-4",
        "name": "M6"
    },
    "-d10009.jpg": {
        "n1": "G#5",
        "n2": "B-4",
        "name": "m7"
    },
    "-d10010.jpg": {
        "n1": "A5",
        "n2": "B-4",
        "name": "M7"
    },
    "-d1005.jpg": {
        "n1": "G4",
        "n2": "C#4",
        "name": "d5"
    },
    "-d1007.jpg": {
        "n1": "A4",
        "n2": "C#4",
        "name": "m6"
    },
    "-d1008.jpg": {
        "n1": "B-4",
        "n2": "C#4",
        "name": "M6"
    },
    "-d1009.jpg": {
        "n1": "B4",
        "n2": "C#4",
        "name": "m7"
    },
    "-d1010.jpg": {
        "n1": "C5",
        "n2": "C#4",
        "name": "M7"
    },
    "-d11005.jpg": {
        "n1": "F5",
        "n2": "B4",
        "name": "d5"
    },
    "-d11007.jpg": {
        "n1": "G5",
        "n2": "B4",
        "name": "m6"
    },
    "-d11008.jpg": {
        "n1": "G#5",
        "n2": "B4",
        "name": "M6"
    },
    "-d11009.jpg": {
        "n1": "A5",
        "n2": "B4",
        "name": "m7"
    },
    "-d11010.jpg": {
        "n1": "B-5",
        "n2": "B4",
        "name": "M7"
    },
    "-d12005.jpg": {
        "n1": "F#5",
        "n2": "C5",
        "name": "d5"
    },
    "-d12007.jpg": {
        "n1": "G#5",
        "n2": "C5",
        "name": "m6"
    },
    "-d12008.jpg": {
        "n1": "A5",
        "n2": "C5",
        "name": "M6"
    },
    "-d12009.jpg": {
        "n1": "B-5",
        "n2": "C5",
        "name": "m7"
    },
    "-d12010.jpg": {
        "n1": "B5",
        "n2": "C5",
        "name": "M7"
    },
    "-d13005.jpg": {
        "n1": "G5",
        "n2": "C#5",
        "name": "d5"
    },
    "-d13007.jpg": {
        "n1": "A5",
        "n2": "C#5",
        "name": "m6"
    },
    "-d13008.jpg": {
        "n1": "B-5",
        "n2": "C#5",
        "name": "M6"
    },
    "-d13009.jpg": {
        "n1": "B5",
        "n2": "C#5",
        "name": "m7"
    },
    "-d13010.jpg": {
        "n1": "C6",
        "n2": "C#5",
        "name": "M7"
    },
    "-d14005.jpg": {
        "n1": "G#5",
        "n2": "D5",
        "name": "d5"
    },
    "-d14007.jpg": {
        "n1": "B-5",
        "n2": "D5",
        "name": "m6"
    },
    "-d14008.jpg": {
        "n1": "B5",
        "n2": "D5",
        "name": "M6"
    },
    "-d14009.jpg": {
        "n1": "C6",
        "n2": "D5",
        "name": "m7"
    },
    "-d15005.jpg": {
        "n1": "A5",
        "n2": "E-5",
        "name": "d5"
    },
    "-d15007.jpg": {
        "n1": "B5",
        "n2": "E-5",
        "name": "m6"
    },
    "-d15008.jpg": {
        "n1": "C6",
        "n2": "E-5",
        "name": "M6"
    },
    "-d16005.jpg": {
        "n1": "B-5",
        "n2": "E5",
        "name": "d5"
    },
    "-d16007.jpg": {
        "n1": "C6",
        "n2": "E5",
        "name": "m6"
    },
    "-d17005.jpg": {
        "n1": "B5",
        "n2": "F5",
        "name": "d5"
    },
    "-d18005.jpg": {
        "n1": "C6",
        "n2": "F#5",
        "name": "d5"
    },
    "-d2005.jpg": {
        "n1": "G#4",
        "n2": "D4",
        "name": "d5"
    },
    "-d2007.jpg": {
        "n1": "B-4",
        "n2": "D4",
        "name": "m6"
    },
    "-d2008.jpg": {
        "n1": "B4",
        "n2": "D4",
        "name": "M6"
    },
    "-d2009.jpg": {
        "n1": "C5",
        "n2": "D4",
        "name": "m7"
    },
    "-d2010.jpg": {
        "n1": "C#5",
        "n2": "D4",
        "name": "M7"
    },
    "-d3005.jpg": {
        "n1": "A4",
        "n2": "E-4",
        "name": "d5"
    },
    "-d3007.jpg": {
        "n1": "B4",
        "n2": "E-4",
        "name": "m6"
    },
    "-d3008.jpg": {
        "n1": "C5",
        "n2": "E-4",
        "name": "M6"
    },
    "-d3009.jpg": {
        "n1": "C#5",
        "n2": "E-4",
        "name": "m7"
    },
    "-d3010.jpg": {
        "n1": "D5",
        "n2": "E-4",
        "name": "M7"
    },
    "-d4005.jpg": {
        "n1": "B-4",
        "n2": "E4",
        "name": "d5"
    },
    "-d4007.jpg": {
        "n1": "C5",
        "n2": "E4",
        "name": "m6"
    },
    "-d4008.jpg": {
        "n1": "C#5",
        "n2": "E4",
        "name": "M6"
    },
    "-d4009.jpg": {
        "n1": "D5",
        "n2": "E4",
        "name": "m7"
    },
    "-d4010.jpg": {
        "n1": "E-5",
        "n2": "E4",
        "name": "M7"
    },
    "-d5.jpg": {
        "n1": "F#4",
        "n2": "C4",
        "name": "d5"
    },
    "-d5005.jpg": {
        "n1": "B4",
        "n2": "F4",
        "name": "d5"
    },
    "-d5007.jpg": {
        "n1": "C#5",
        "n2": "F4",
        "name": "m6"
    },
    "-d5008.jpg": {
        "n1": "D5",
        "n2": "F4",
        "name": "M6"
    },
    "-d5009.jpg": {
        "n1": "E-5",
        "n2": "F4",
        "name": "m7"
    },
    "-d5010.jpg": {
        "n1": "E5",
        "n2": "F4",
        "name": "M7"
    },
    "-d6005.jpg": {
        "n1": "C5",
        "n2": "F#4",
        "name": "d5"
    },
    "-d6007.jpg": {
        "n1": "D5",
        "n2": "F#4",
        "name": "m6"
    },
    "-d6008.jpg": {
        "n1": "E-5",
        "n2": "F#4",
        "name": "M6"
    },
    "-d6009.jpg": {
        "n1": "E5",
        "n2": "F#4",
        "name": "m7"
    },
    "-d6010.jpg": {
        "n1": "F5",
        "n2": "F#4",
        "name": "M7"
    },
    "-d7.jpg": {
        "n1": "G#4",
        "n2": "C4",
        "name": "m6"
    },
    "-d7005.jpg": {
        "n1": "C#5",
        "n2": "G4",
        "name": "d5"
    },
    "-d7007.jpg": {
        "n1": "E-5",
        "n2": "G4",
        "name": "m6"
    },
    "-d7008.jpg": {
        "n1": "E5",
        "n2": "G4",
        "name": "M6"
    },
    "-d7009.jpg": {
        "n1": "F5",
        "n2": "G4",
        "name": "m7"
    },
    "-d7010.jpg": {
        "n1": "F#5",
        "n2": "G4",
        "name": "M7"
    },
    "-d8.jpg": {
        "n1": "A4",
        "n2": "C4",
        "name": "M6"
    },
    "-d8005.jpg": {
        "n1": "D5",
        "n2": "G#4",
        "name": "d5"
    },
    "-d8007.jpg": {
        "n1": "E5",
        "n2": "G#4",
        "name": "m6"
    },
    "-d8008.jpg": {
        "n1": "F5",
        "n2": "G#4",
        "name": "M6"
    },
    "-d8009.jpg": {
        "n1": "F#5",
        "n2": "G#4",
        "name": "m7"
    },
    "-d8010.jpg": {
        "n1": "G5",
        "n2": "G#4",
        "name": "M7"
    },
    "-d9.jpg": {
        "n1": "B-4",
        "n2": "C4",
        "name": "m7"
    },
    "-d9005.jpg": {
        "n1": "E-5",
        "n2": "A4",
        "name": "d5"
    },
    "-d9007.jpg": {
        "n1": "F5",
        "n2": "A4",
        "name": "m6"
    },
    "-d9008.jpg": {
        "n1": "F#5",
        "n2": "A4",
        "name": "M6"
    },
    "-d9009.jpg": {
        "n1": "G5",
        "n2": "A4",
        "name": "m7"
    },
    "-d9010.jpg": {
        "n1": "G#5",
        "n2": "A4",
        "name": "M7"
    },
    "-e1.jpg": {
        "n1": "D4",
        "n2": "C4",
        "name": "M2"
    },
    "-e10001.jpg": {
        "n1": "C5",
        "n2": "B-4",
        "name": "M2"
    },
    "-e10003.jpg": {
        "n1": "D5",
        "n2": "B-4",
        "name": "M3"
    },
    "-e10006.jpg": {
        "n1": "F5",
        "n2": "B-4",
        "name": "P5"
    },
    "-e1001.jpg": {
        "n1": "E-4",
        "n2": "C#4",
        "name": "M2"
    },
    "-e10011.jpg": {
        "n1": "B-5",
        "n2": "B-4",
        "name": "P8"
    },
    "-e1003.jpg": {
        "n1": "F4",
        "n2": "C#4",
        "name": "M3"
    },
    "-e1006.jpg": {
        "n1": "G#4",
        "n2": "C#4",
        "name": "P5"
    },
    "-e1011.jpg": {
        "n1": "C#5",
        "n2": "C#4",
        "name": "P8"
    },
    "-e11.jpg": {
        "n1": "C5",
        "n2": "C4",
        "name": "P8"
    },
    "-e11001.jpg": {
        "n1": "C#5",
        "n2": "B4",
        "name": "M2"
    },
    "-e11003.jpg": {
        "n1": "E-5",
        "n2": "B4",
        "name": "M3"
    },
    "-e11006.jpg": {
        "n1": "F#5",
        "n2": "B4",
        "name": "P5"
    },
    "-e11011.jpg": {
        "n1": "B5",
        "n2": "B4",
        "name": "P8"
    },
    "-e12001.jpg": {
        "n1": "D5",
        "n2": "C5",
        "name": "M2"
    },
    "-e12003.jpg": {
        "n1": "E5",
        "n2": "C5",
        "name": "M3"
    },
    "-e12006.jpg": {
        "n1": "G5",
        "n2": "C5",
        "name": "P5"
    },
    "-e12011.jpg": {
        "n1": "C6",
        "n2": "C5",
        "name": "P8"
    },
    "-e13001.jpg": {
        "n1": "E-5",
        "n2": "C#5",
        "name": "M2"
    },
    "-e13003.jpg": {
        "n1": "F5",
        "n2": "C#5",
        "name": "M3"
    },
    "-e13006.jpg": {
        "n1": "G#5",
        "n2": "C#5",
        "name": "P5"
    },
    "-e14001.jpg": {
        "n1": "E5",
        "n2": "D5",
        "name": "M2"
    },
    "-e14003.jpg": {
        "n1": "F#5",
        "n2": "D5",
        "name": "M3"
    },
    "-e14006.jpg": {
        "n1": "A5",
        "n2": "D5",
        "name": "P5"
    },
    "-e15001.jpg": {
        "n1": "F5",
        "n2": "E-5",
        "name": "M2"
    },
    "-e15003.jpg": {
        "n1": "G5",
        "n2": "E-5",
        "name": "M3"
    },
    "-e15006.jpg": {
        "n1": "B-5",
        "n2": "E-5",
        "name": "P5"
    },
    "-e16001.jpg": {
        "n1": "F#5",
        "n2": "E5",
        "name": "M2"
    },
    "-e16003.jpg": {
        "n1": "G#5",
        "n2": "E5",
        "name": "M3"
    },
    "-e16006.jpg": {
        "n1": "B5",
        "n2": "E5",
        "name": "P5"
    },
    "-e17001.jpg": {
        "n1": "G5",
        "n2": "F5",
        "name": "M2"
    },
    "-e17003.jpg": {
        "n1": "A5",
        "n2": "F5",
        "name": "M3"
    },
    "-e17006.jpg": {
        "n1": "C6",
        "n2": "F5",
        "name": "P5"
    },
    "-e18001.jpg": {
        "n1": "G#5",
        "n2": "F#5",
        "name": "M2"
    },
    "-e18003.jpg": {
        "n1": "B-5",
        "n2": "F#5",
        "name": "M3"
    },
    "-e19001.jpg": {
        "n1": "A5",
        "n2": "G5",
        "name": "M2"
    },
    "-e19003.jpg": {
        "n1": "B5",
        "n2": "G5",
        "name": "M3"
    },
    "-e20001.jpg": {
        "n1": "B-5",
        "n2": "G#5",
        "name": "M2"
    },
    "-e20003.jpg": {
        "n1": "C6",
        "n2": "G#5",
        "name": "M3"
    },
    "-e2001.jpg": {
        "n1": "E4",
        "n2": "D4",
        "name": "M2"
    },
    "-e2003.jpg": {
        "n1": "F#4",
        "n2": "D4",
        "name": "M3"
    },
    "-e2006.jpg": {
        "n1": "A4",
        "n2": "D4",
        "name": "P5"
    },
    "-e2011.jpg": {
        "n1": "D5",
        "n2": "D4",
        "name": "P8"
    },
    "-e21001.jpg": {
        "n1": "B5",
        "n2": "A5",
        "name": "M2"
    },
    "-e22001.jpg": {
        "n1": "C6",
        "n2": "B-5",
        "name": "M2"
    },
    "-e3.jpg": {
        "n1": "E4",
        "n2": "C4",
        "name": "M3"
    },
    "-e3001.jpg": {
        "n1": "F4",
        "n2": "E-4",
        "name": "M2"
    },
    "-e3003.jpg": {
        "n1": "G4",
        "n2": "E-4",
        "name": "M3"
    },
    "-e3006.jpg": {
        "n1": "B-4",
        "n2": "E-4",
        "name": "P5"
    },
    "-e3011.jpg": {
        "n1": "E-5",
        "n2": "E-4",
        "name": "P8"
    },
    "-e4001.jpg": {
        "n1": "F#4",
        "n2": "E4",
        "name": "M2"
    },
    "-e4003.jpg": {
        "n1": "G#4",
        "n2": "E4",
        "name": "M3"
    },
    "-e4006.jpg": {
        "n1": "B4",
        "n2": "E4",
        "name": "P5"
    },
    "-e4011.jpg": {
        "n1": "E5",
        "n2": "E4",
        "name": "P8"
    },
    "-e5001.jpg": {
        "n1": "G4",
        "n2": "F4",
        "name": "M2"
    },
    "-e5003.jpg": {
        "n1": "A4",
        "n2": "F4",
        "name": "M3"
    },
    "-e5006.jpg": {
        "n1": "C5",
        "n2": "F4",
        "name": "P5"
    },
    "-e5011.jpg": {
        "n1": "F5",
        "n2": "F4",
        "name": "P8"
    },
    "-e6.jpg": {
        "n1": "G4",
        "n2": "C4",
        "name": "P5"
    },
    "-e6001.jpg": {
        "n1": "G#4",
        "n2": "F#4",
        "name": "M2"
    },
    "-e6003.jpg": {
        "n1": "B-4",
        "n2": "F#4",
        "name": "M3"
    },
    "-e6006.jpg": {
        "n1": "C#5",
        "n2": "F#4",
        "name": "P5"
    },
    "-e6011.jpg": {
        "n1": "F#5",
        "n2": "F#4",
        "name": "P8"
    },
    "-e7001.jpg": {
        "n1": "A4",
        "n2": "G4",
        "name": "M2"
    },
    "-e7003.jpg": {
        "n1": "B4",
        "n2": "G4",
        "name": "M3"
    },
    "-e7006.jpg": {
        "n1": "D5",
        "n2": "G4",
        "name": "P5"
    },
    "-e7011.jpg": {
        "n1": "G5",
        "n2": "G4",
        "name": "P8"
    },
    "-e8001.jpg": {
        "n1": "B-4",
        "n2": "G#4",
        "name": "M2"
    },
    "-e8003.jpg": {
        "n1": "C5",
        "n2": "G#4",
        "name": "M3"
    },
    "-e8006.jpg": {
        "n1": "E-5",
        "n2": "G#4",
        "name": "P5"
    },
    "-e8011.jpg": {
        "n1": "G#5",
        "n2": "G#4",
        "name": "P8"
    },
    "-e9001.jpg": {
        "n1": "B4",
        "n2": "A4",
        "name": "M2"
    },
    "-e9003.jpg": {
        "n1": "C#5",
        "n2": "A4",
        "name": "M3"
    },
    "-e9006.jpg": {
        "n1": "E5",
        "n2": "A4",
        "name": "P5"
    },
    "-e9011.jpg": {
        "n1": "A5",
        "n2": "A4",
        "name": "P8"
    },
    "-m0.jpg": {
        "n1": "C#4",
        "n2": "C4",
        "name": "m2"
    },
    "-m1000.jpg": {
        "n1": "D4",
        "n2": "C#4",
        "name": "m2"
    },
    "-m10000.jpg": {
        "n1": "B4",
        "n2": "B-4",
        "name": "m2"
    },
    "-m10002.jpg": {
        "n1": "C#5",
        "n2": "B-4",
        "name": "m3"
    },
    "-m10004.jpg": {
        "n1": "E-5",
        "n2": "B-4",
        "name": "P4"
    },
    "-m1002.jpg": {
        "n1": "E4",
        "n2": "C#4",
        "name": "m3"
    },
    "-m1004.jpg": {
        "n1": "F#4",
        "n2": "C#4",
        "name": "P4"
    },
    "-m11000.jpg": {
        "n1": "C5",
        "n2": "B4",
        "name": "m2"
    },
    "-m11002.jpg": {
        "n1": "D5",
        "n2": "B4",
        "name": "m3"
    },
    "-m11004.jpg": {
        "n1": "E5",
        "n2": "B4",
        "name": "P4"
    },
    "-m12000.jpg": {
        "n1": "C#5",
        "n2": "C5",
        "name": "m2"
    },
    "-m12002.jpg": {
        "n1": "E-5",
        "n2": "C5",
        "name": "m3"
    },
    "-m12004.jpg": {
        "n1": "F5",
        "n2": "C5",
        "name": "P4"
    },
    "-m13000.jpg": {
        "n1": "D5",
        "n2": "C#5",
        "name": "m2"
    },
    "-m13002.jpg": {
        "n1": "E5",
        "n2": "C#5",
        "name": "m3"
    },
    "-m13004.jpg": {
        "n1": "F#5",
        "n2": "C#5",
        "name": "P4"
    },
    "-m14000.jpg": {
        "n1": "E-5",
        "n2": "D5",
        "name": "m2"
    },
    "-m14002.jpg": {
        "n1": "F5",
        "n2": "D5",
        "name": "m3"
    },
    "-m14004.jpg": {
        "n1": "G5",
        "n2": "D5",
        "name": "P4"
    },
    "-m15000.jpg": {
        "n1": "E5",
        "n2": "E-5",
        "name": "m2"
    },
    "-m15002.jpg": {
        "n1": "F#5",
        "n2": "E-5",
        "name": "m3"
    },
    "-m15004.jpg": {
        "n1": "G#5",
        "n2": "E-5",
        "name": "P4"
    },
    "-m16000.jpg": {
        "n1": "F5",
        "n2": "E5",
        "name": "m2"
    },
    "-m16002.jpg": {
        "n1": "G5",
        "n2": "E5",
        "name": "m3"
    },
    "-m16004.jpg": {
        "n1": "A5",
        "n2": "E5",
        "name": "P4"
    },
    "-m17000.jpg": {
        "n1": "F#5",
        "n2": "F5",
        "name": "m2"
    },
    "-m17002.jpg": {
        "n1": "G#5",
        "n2": "F5",
        "name": "m3"
    },
    "-m17004.jpg": {
        "n1": "B-5",
        "n2": "F5",
        "name": "P4"
    },
    "-m18000.jpg": {
        "n1": "G5",
        "n2": "F#5",
        "name": "m2"
    },
    "-m18002.jpg": {
        "n1": "A5",
        "n2": "F#5",
        "name": "m3"
    },
    "-m18004.jpg": {
        "n1": "B5",
        "n2": "F#5",
        "name": "P4"
    },
    "-m19000.jpg": {
        "n1": "G#5",
        "n2": "G5",
        "name": "m2"
    },
    "-m19002.jpg": {
        "n1": "B-5",
        "n2": "G5",
        "name": "m3"
    },
    "-m19004.jpg": {
        "n1": "C6",
        "n2": "G5",
        "name": "P4"
    },
    "-m2.jpg": {
        "n1": "E-4",
        "n2": "C4",
        "name": "m3"
    },
    "-m2000.jpg": {
        "n1": "E-4",
        "n2": "D4",
        "name": "m2"
    },
    "-m20000.jpg": {
        "n1": "A5",
        "n2": "G#5",
        "name": "m2"
    },
    "-m20002.jpg": {
        "n1": "B5",
        "n2": "G#5",
        "name": "m3"
    },
    "-m2002.jpg": {
        "n1": "F4",
        "n2": "D4",
        "name": "m3"
    },
    "-m2004.jpg": {
        "n1": "G4",
        "n2": "D4",
        "name": "P4"
    },
    "-m21000.jpg": {
        "n1": "B-5",
        "n2": "A5",
        "name": "m2"
    },
    "-m21002.jpg": {
        "n1": "C6",
        "n2": "A5",
        "name": "m3"
    },
    "-m22000.jpg": {
        "n1": "B5",
        "n2": "B-5",
        "name": "m2"
    },
    "-m23000.jpg": {
        "n1": "C6",
        "n2": "B5",
        "name": "m2"
    },
    "-m3000.jpg": {
        "n1": "E4",
        "n2": "E-4",
        "name": "m2"
    },
    "-m3002.jpg": {
        "n1": "F#4",
        "n2": "E-4",
        "name": "m3"
    },
    "-m3004.jpg": {
        "n1": "G#4",
        "n2": "E-4",
        "name": "P4"
    },
    "-m4.jpg": {
        "n1": "F4",
        "n2": "C4",
        "name": "P4"
    },
    "-m4000.jpg": {
        "n1": "F4",
        "n2": "E4",
        "name": "m2"
    },
    "-m4002.jpg": {
        "n1": "G4",
        "n2": "E4",
        "name": "m3"
    },
    "-m4004.jpg": {
        "n1": "A4",
        "n2": "E4",
        "name": "P4"
    },
    "-m5000.jpg": {
        "n1": "F#4",
        "n2": "F4",
        "name": "m2"
    },
    "-m5002.jpg": {
        "n1": "G#4",
        "n2": "F4",
        "name": "m3"
    },
    "-m5004.jpg": {
        "n1": "B-4",
        "n2": "F4",
        "name": "P4"
    },
    "-m6000.jpg": {
        "n1": "G4",
        "n2": "F#4",
        "name": "m2"
    },
    "-m6002.jpg": {
        "n1": "A4",
        "n2": "F#4",
        "name": "m3"
    },
    "-m6004.jpg": {
        "n1": "B4",
        "n2": "F#4",
        "name": "P4"
    },
    "-m7000.jpg": {
        "n1": "G#4",
        "n2": "G4",
        "name": "m2"
    },
    "-m7002.jpg": {
        "n1": "B-4",
        "n2": "G4",
        "name": "m3"
    },
    "-m7004.jpg": {
        "n1": "C5",
        "n2": "G4",
        "name": "P4"
    },
    "-m8000.jpg": {
        "n1": "A4",
        "n2": "G#4",
        "name": "m2"
    },
    "-m8002.jpg": {
        "n1": "B4",
        "n2": "G#4",
        "name": "m3"
    },
    "-m8004.jpg": {
        "n1": "C#5",
        "n2": "G#4",
        "name": "P4"
    },
    "-m9000.jpg": {
        "n1": "B-4",
        "n2": "A4",
        "name": "m2"
    },
    "-m9002.jpg": {
        "n1": "C5",
        "n2": "A4",
        "name": "m3"
    },
    "-m9004.jpg": {
        "n1": "D5",
        "n2": "A4",
        "name": "P4"
    },
    "d10.jpg": {
        "n1": "C4",
        "n2": "B4",
        "name": "M7"
    },
    "d10005.jpg": {
        "n1": "B-4",
        "n2": "E5",
        "name": "d5"
    },
    "d10007.jpg": {
        "n1": "B-4",
        "n2": "F#5",
        "name": "m6"
    },
    "d10008.jpg": {
        "n1": "B-4",
        "n2": "G5",
        "name": "M6"
    },
    "d10009.jpg": {
        "n1": "B-4",
        "n2": "G#5",
        "name": "m7"
    },
    "d10010.jpg": {
        "n1": "B-4",
        "n2": "A5",
        "name": "M7"
    },
    "d1005.jpg": {
        "n1": "C#4",
        "n2": "G4",
        "name": "d5"
    },
    "d1007.jpg": {
        "n1": "C#4",
        "n2": "A4",
        "name": "m6"
    },
    "d1008.jpg": {
        "n1": "C#4",
        "n2": "B-4",
        "name": "M6"
    },
    "d1009.jpg": {
        "n1": "C#4",
        "n2": "B4",
        "name": "m7"
    },
    "d1010.jpg": {
        "n1": "C#4",
        "n2": "C5",
        "name": "M7"
    },
    "d11005.jpg": {
        "n1": "B4",
        "n2": "F5",
        "name": "d5"
    },
    "d11007.jpg": {
        "n1": "B4",
        "n2": "G5",
        "name": "m6"
    },
    "d11008.jpg": {
        "n1": "B4",
        "n2": "G#5",
        "name": "M6"
    },
    "d11009.jpg": {
        "n1": "B4",
        "n2": "A5",
        "name": "m7"
    },
    "d11010.jpg": {
        "n1": "B4",
        "n2": "B-5",
        "name": "M7"
    },
    "d12005.jpg": {
        "n1": "C5",
        "n2": "F#5",
        "name": "d5"
    },
    "d12007.jpg": {
        "n1": "C5",
        "n2": "G#5",
        "name": "m6"
    },
    "d12008.jpg": {
        "n1": "C5",
        "n2": "A5",
        "name": "M6"
    },
    "d12009.jpg": {
        "n1": "C5",
        "n2": "B-5",
        "name": "m7"
    },
    "d12010.jpg": {
        "n1": "C5",
        "n2": "B5",
        "name": "M7"
    },
    "d13005.jpg": {
        "n1": "C#5",
        "n2": "G5",
        "name": "d5"
    },
    "d13007.jpg": {
        "n1": "C#5",
        "n2": "A5",
        "name": "m6"
    },
    "d13008.jpg": {
        "n1": "C#5",
        "n2": "B-5",
        "name": "M6"
    },
    "d13009.jpg": {
        "n1": "C#5",
        "n2": "B5",
        "name": "m7"
    },
    "d13010.jpg": {
        "n1": "C#5",
        "n2": "C6",
        "name": "M7"
    },
    "d14005.jpg": {
        "n1": "D5",
        "n2": "G#5",
        "name": "d5"
    },
    "d14007.jpg": {
        "n1": "D5",
        "n2": "B-5",
        "name": "m6"
    },
    "d14008.jpg": {
        "n1": "D5",
        "n2": "B5",
        "name": "M6"
    },
    "d14009.jpg": {
        "n1": "D5",
        "n2": "C6",
        "name": "m7"
    },
    "d15005.jpg": {
        "n1": "E-5",
        "n2": "A5",
        "name": "d5"
    },
    "d15007.jpg": {
        "n1": "E-5",
        "n2": "B5",
        "name": "m6"
    },
    "d15008.jpg": {
        "n1": "E-5",
        "n2": "C6",
        "name": "M6"
    },
    "d16005.jpg": {
        "n1": "E5",
        "n2": "B-5",
        "name": "d5"
    },
    "d16007.jpg": {
        "n1": "E5",
        "n2": "C6",
        "name": "m6"
    },
    "d17005.jpg": {
        "n1": "F5",
        "n2": "B5",
        "name": "d5"
    },
    "d18005.jpg": {
        "n1": "F#5",
        "n2": "C6",
        "name": "d5"
    },
    "d2005.jpg": {
        "n1": "D4",
        "n2": "G#4",
        "name": "d5"
    },
    "d2007.jpg": {
        "n1": "D4",
        "n2": "B-4",
        "name": "m6"
    },
    "d2008.jpg": {
        "n1": "D4",
        "n2": "B4",
        "name": "M6"
    },
    "d2009.jpg": {
        "n1": "D4",
        "n2": "C5",
        "name": "m7"
    },
    "d2010.jpg": {
        "n1": "D4",
        "n2": "C#5",
        "name": "M7"
    },
    "d3005.jpg": {
        "n1": "E-4",
        "n2": "A4",
        "name": "d5"
    },
    "d3007.jpg": {
        "n1": "E-4",
        "n2": "B4",
        "name": "m6"
    },
    "d3008.jpg": {
        "n1": "E-4",
        "n2": "C5",
        "name": "M6"
    },
    "d3009.jpg": {
        "n1": "E-4",
        "n2": "C#5",
        "name": "m7"
    },
    "d3010.jpg": {
        "n1": "E-4",
        "n2": "D5",
        "name": "M7"
    },
    "d4005.jpg": {
        "n1": "E4",
        "n2": "B-4",
        "name": "d5"
    },
    "d4007.jpg": {
        "n1": "E4",
        "n2": "C5",
        "name": "m6"
    },
    "d4008.jpg": {
        "n1": "E4",
        "n2": "C#5",
        "name": "M6"
    },
    "d4009.jpg": {
        "n1": "E4",
        "n2": "D5",
        "name": "m7"
    },
    "d4010.jpg": {
        "n1": "E4",
        "n2": "E-5",
        "name": "M7"
    },
    "d5.jpg": {
        "n1": "C4",
        "n2": "F#4",
        "name": "d5"
    },
    "d5005.jpg": {
        "n1": "F4",
        "n2": "B4",
        "name": "d5"
    },
    "d5007.jpg": {
        "n1": "F4",
        "n2": "C#5",
        "name": "m6"
    },
    "d5008.jpg": {
        "n1": "F4",
        "n2": "D5",
        "name": "M6"
    },
    "d5009.jpg": {
        "n1": "F4",
        "n2": "E-5",
        "name": "m7"
    },
    "d5010.jpg": {
        "n1": "F4",
        "n2": "E5",
        "name": "M7"
    },
    "d6005.jpg": {
        "n1": "F#4",
        "n2": "C5",
        "name": "d5"
    },
    "d6007.jpg": {
        "n1": "F#4",
        "n2": "D5",
        "name": "m6"
    },
    "d6008.jpg": {
        "n1": "F#4",
        "n2": "E-5",
        "name": "M6"
    },
    "d6009.jpg": {
        "n1": "F#4",
        "n2": "E5",
        "name": "m7"
    },
    "d6010.jpg": {
        "n1": "F#4",
        "n2": "F5",
        "name": "M7"
    },
    "d7.jpg": {
        "n1": "C4",
        "n2": "G#4",
        "name": "m6"
    },
    "d7005.jpg": {
        "n1": "G4",
        "n2": "C#5",
        "name": "d5"
    },
    "d7007.jpg": {
        "n1": "G4",
        "n2": "E-5",
        "name": "m6"
    },
    "d7008.jpg": {
        "n1": "G4",
        "n2": "E5",
        "name": "M6"
    },
    "d7009.jpg": {
        "n1": "G4",
        "n2": "F5",
        "name": "m7"
    },
    "d7010.jpg": {
        "n1": "G4",
        "n2": "F#5",
        "name": "M7"
    },
    "d8.jpg": {
        "n1": "C4",
        "n2": "A4",
        "name": "M6"
    },
    "d8005.jpg": {
        "n1": "G#4",
        "n2": "D5",
        "name": "d5"
    },
    "d8007.jpg": {
        "n1": "G#4",
        "n2": "E5",
        "name": "m6"
    },
    "d8008.jpg": {
        "n1": "G#4",
        "n2": "F5",
        "name": "M6"
    },
    "d8009.jpg": {
        "n1": "G#4",
        "n2": "F#5",
        "name": "m7"
    },
    "d8010.jpg": {
        "n1": "G#4",
        "n2": "G5",
        "name": "M7"
    },
    "d9.jpg": {
        "n1": "C4",
        "n2": "B-4",
        "name": "m7"
    },
    "d9005.jpg": {
        "n1": "A4",
        "n2": "E-5",
        "name": "d5"
    },
    "d9007.jpg": {
        "n1": "A4",
        "n2": "F5",
        "name": "m6"
    },
    "d9008.jpg": {
        "n1": "A4",
        "n2": "F#5",
        "name": "M6"
    },
    "d9009.jpg": {
        "n1": "A4",
        "n2": "G5",
        "name": "m7"
    },
    "d9010.jpg": {
        "n1": "A4",
        "n2": "G#5",
        "name": "M7"
    },
    "e1.jpg": {
        "n1": "C4",
        "n2": "D4",
        "name": "M2"
    },
    "e10001.jpg": {
        "n1": "B-4",
        "n2": "C5",
        "name": "M2"
    },
    "e10003.jpg": {
        "n1": "B-4",
        "n2": "D5",
        "name": "M3"
    },
    "e10006.jpg": {
        "n1": "B-4",
        "n2": "F5",
        "name": "P5"
    },
    "e1001.jpg": {
        "n1": "C#4",
        "n2": "E-4",
        "name": "M2"
    },
    "e10011.jpg": {
        "n1": "B-4",
        "n2": "B-5",
        "name": "P8"
    },
    "e1003.jpg": {
        "n1": "C#4",
        "n2": "F4",
        "name": "M3"
    },
    "e1006.jpg": {
        "n1": "C#4",
        "n2": "G#4",
        "name": "P5"
    },
    "e1011.jpg": {
        "n1": "C#4",
        "n2": "C#5",
        "name": "P8"
    },
    "e11.jpg": {
        "n1": "C4",
        "n2": "C5",
        "name": "P8"
    },
    "e11001.jpg": {
        "n1": "B4",
        "n2": "C#5",
        "name": "M2"
    },
    "e11003.jpg": {
        "n1": "B4",
        "n2": "E-5",
        "name": "M3"
    },
    "e11006.jpg": {
        "n1": "B4",
        "n2": "F#5",
        "name": "P5"
    },
    "e11011.jpg": {
        "n1": "B4",
        "n2": "B5",
        "name": "P8"
    },
    "e12001.jpg": {
        "n1": "C5",
        "n2": "D5",
        "name": "M2"
    },
    "e12003.jpg": {
        "n1": "C5",
        "n2": "E5",
        "name": "M3"
    },
    "e12006.jpg": {
        "n1": "C5",
        "n2": "G5",
        "name": "P5"
    },
    "e12011.jpg": {
        "n1": "C5",
        "n2": "C6",
        "name": "P8"
    },
    "e13001.jpg": {
        "n1": "C#5",
        "n2": "E-5",
        "name": "M2"
    },
    "e13003.jpg": {
        "n1": "C#5",
        "n2": "F5",
        "name": "M3"
    },
    "e13006.jpg": {
        "n1": "C#5",
        "n2": "G#5",
        "name": "P5"
    },
    "e14001.jpg": {
        "n1": "D5",
        "n2": "E5",
        "name": "M2"
    },
    "e14003.jpg": {
        "n1": "D5",
        "n2": "F#5",
        "name": "M3"
    },
    "e14006.jpg": {
        "n1": "D5",
        "n2": "A5",
        "name": "P5"
    },
    "e15001.jpg": {
        "n1": "E-5",
        "n2": "F5",
        "name": "M2"
    },
    "e15003.jpg": {
        "n1": "E-5",
        "n2": "G5",
        "name": "M3"
    },
    "e15006.jpg": {
        "n1": "E-5",
        "n2": "B-5",
        "name": "P5"
    },
    "e16001.jpg": {
        "n1": "E5",
        "n2": "F#5",
        "name": "M2"
    },
    "e16003.jpg": {
        "n1": "E5",
        "n2": "G#5",
        "name": "M3"
    },
    "e16006.jpg": {
        "n1": "E5",
        "n2": "B5",
        "name": "P5"
    },
    "e17001.jpg": {
        "n1": "F5",
        "n2": "G5",
        "name": "M2"
    },
    "e17003.jpg": {
        "n1": "F5",
        "n2": "A5",
        "name": "M3"
    },
    "e17006.jpg": {
        "n1": "F5",
        "n2": "C6",
        "name": "P5"
    },
    "e18001.jpg": {
        "n1": "F#5",
        "n2": "G#5",
        "name": "M2"
    },
    "e18003.jpg": {
        "n1": "F#5",
        "n2": "B-5",
        "name": "M3"
    },
    "e19001.jpg": {
        "n1": "G5",
        "n2": "A5",
        "name": "M2"
    },
    "e19003.jpg": {
        "n1": "G5",
        "n2": "B5",
        "name": "M3"
    },
    "e20001.jpg": {
        "n1": "G#5",
        "n2": "B-5",
        "name": "M2"
    },
    "e20003.jpg": {
        "n1": "G#5",
        "n2": "C6",
        "name": "M3"
    },
    "e2001.jpg": {
        "n1": "D4",
        "n2": "E4",
        "name": "M2"
    },
    "e2003.jpg": {
        "n1": "D4",
        "n2": "F#4",
        "name": "M3"
    },
    "e2006.jpg": {
        "n1": "D4",
        "n2": "A4",
        "name": "P5"
    },
    "e2011.jpg": {
        "n1": "D4",
        "n2": "D5",
        "name": "P8"
    },
    "e21001.jpg": {
        "n1": "A5",
        "n2": "B5",
        "name": "M2"
    },
    "e22001.jpg": {
        "n1": "B-5",
        "n2": "C6",
        "name": "M2"
    },
    "e3.jpg": {
        "n1": "C4",
        "n2": "E4",
        "name": "M3"
    },
    "e3001.jpg": {
        "n1": "E-4",
        "n2": "F4",
        "name": "M2"
    },
    "e3003.jpg": {
        "n1": "E-4",
        "n2": "G4",
        "name": "M3"
    },
    "e3006.jpg": {
        "n1": "E-4",
        "n2": "B-4",
        "name": "P5"
    },
    "e3011.jpg": {
        "n1": "E-4",
        "n2": "E-5",
        "name": "P8"
    },
    "e4001.jpg": {
        "n1": "E4",
        "n2": "F#4",
        "name": "M2"
    },
    "e4003.jpg": {
        "n1": "E4",
        "n2": "G#4",
        "name": "M3"
    },
    "e4006.jpg": {
        "n1": "E4",
        "n2": "B4",
        "name": "P5"
    },
    "e4011.jpg": {
        "n1": "E4",
        "n2": "E5",
        "name": "P8"
    },
    "e5001.jpg": {
        "n1": "F4",
        "n2": "G4",
        "name": "M2"
    },
    "e5003.jpg": {
        "n1": "F4",
        "n2": "A4",
        "name": "M3"
    },
    "e5006.jpg": {
        "n1": "F4",
        "n2": "C5",
        "name": "P5"
    },
    "e5011.jpg": {
        "n1": "F4",
        "n2": "F5",
        "name": "P8"
    },
    "e6.jpg": {
        "n1": "C4",
        "n2": "G4",
        "name": "P5"
    },
    "e6001.jpg": {
        "n1": "F#4",
        "n2": "G#4",
        "name": "M2"
    },
    "e6003.jpg": {
        "n1": "F#4",
        "n2": "B-4",
        "name": "M3"
    },
    "e6006.jpg": {
        "n1": "F#4",
        "n2": "C#5",
        "name": "P5"
    },
    "e6011.jpg": {
        "n1": "F#4",
        "n2": "F#5",
        "name": "P8"
    },
    "e7001.jpg": {
        "n1": "G4",
        "n2": "A4",
        "name": "M2"
    },
    "e7003.jpg": {
        "n1": "G4",
        "n2": "B4",
        "name": "M3"
    },
    "e7006.jpg": {
        "n1": "G4",
        "n2": "D5",
        "name": "P5"
    },
    "e7011.jpg": {
        "n1": "G4",
        "n2": "G5",
        "name": "P8"
    },
    "e8001.jpg": {
        "n1": "G#4",
        "n2": "B-4",
        "name": "M2"
    },
    "e8003.jpg": {
        "n1": "G#4",
        "n2": "C5",
        "name": "M3"
    },
    "e8006.jpg": {
        "n1": "G#4",
        "n2": "E-5",
        "name": "P5"
    },
    "e8011.jpg": {
        "n1": "G#4",
        "n2": "G#5",
        "name": "P8"
    },
    "e9001.jpg": {
        "n1": "A4",
        "n2": "B4",
        "name": "M2"
    },
    "e9003.jpg": {
        "n1": "A4",
        "n2": "C#5",
        "name": "M3"
    },
    "e9006.jpg": {
        "n1": "A4",
        "n2": "E5",
        "name": "P5"
    },
    "e9011.jpg": {
        "n1": "A4",
        "n2": "A5",
        "name": "P8"
    },
    "m0.jpg": {
        "n1": "C4",
        "n2": "C#4",
        "name": "m2"
    },
    "m1000.jpg": {
        "n1": "C#4",
        "n2": "D4",
        "name": "m2"
    },
    "m10000.jpg": {
        "n1": "B-4",
        "n2": "B4",
        "name": "m2"
    },
    "m10002.jpg": {
        "n1": "B-4",
        "n2": "C#5",
        "name": "m3"
    },
    "m10004.jpg": {
        "n1": "B-4",
        "n2": "E-5",
        "name": "P4"
    },
    "m1002.jpg": {
        "n1": "C#4",
        "n2": "E4",
        "name": "m3"
    },
    "m1004.jpg": {
        "n1": "C#4",
        "n2": "F#4",
        "name": "P4"
    },
    "m11000.jpg": {
        "n1": "B4",
        "n2": "C5",
        "name": "m2"
    },
    "m11002.jpg": {
        "n1": "B4",
        "n2": "D5",
        "name": "m3"
    },
    "m11004.jpg": {
        "n1": "B4",
        "n2": "E5",
        "name": "P4"
    },
    "m12000.jpg": {
        "n1": "C5",
        "n2": "C#5",
        "name": "m2"
    },
    "m12002.jpg": {
        "n1": "C5",
        "n2": "E-5",
        "name": "m3"
    },
    "m12004.jpg": {
        "n1": "C5",
        "n2": "F5",
        "name": "P4"
    },
    "m13000.jpg": {
        "n1": "C#5",
        "n2": "D5",
        "name": "m2"
    },
    "m13002.jpg": {
        "n1": "C#5",
        "n2": "E5",
        "name": "m3"
    },
    "m13004.jpg": {
        "n1": "C#5",
        "n2": "F#5",
        "name": "P4"
    },
    "m14000.jpg": {
        "n1": "D5",
        "n2": "E-5",
        "name": "m2"
    },
    "m14002.jpg": {
        "n1": "D5",
        "n2": "F5",
        "name": "m3"
    },
    "m14004.jpg": {
        "n1": "D5",
        "n2": "G5",
        "name": "P4"
    },
    "m15000.jpg": {
        "n1": "E-5",
        "n2": "E5",
        "name": "m2"
    },
    "m15002.jpg": {
        "n1": "E-5",
        "n2": "F#5",
        "name": "m3"
    },
    "m15004.jpg": {
        "n1": "E-5",
        "n2": "G#5",
        "name": "P4"
    },
    "m16000.jpg": {
        "n1": "E5",
        "n2": "F5",
        "name": "m2"
    },
    "m16002.jpg": {
        "n1": "E5",
        "n2": "G5",
        "name": "m3"
    },
    "m16004.jpg": {
        "n1": "E5",
        "n2": "A5",
        "name": "P4"
    },
    "m17000.jpg": {
        "n1": "F5",
        "n2": "F#5",
        "name": "m2"
    },
    "m17002.jpg": {
        "n1": "F5",
        "n2": "G#5",
        "name": "m3"
    },
    "m17004.jpg": {
        "n1": "F5",
        "n2": "B-5",
        "name": "P4"
    },
    "m18000.jpg": {
        "n1": "F#5",
        "n2": "G5",
        "name": "m2"
    },
    "m18002.jpg": {
        "n1": "F#5",
        "n2": "A5",
        "name": "m3"
    },
    "m18004.jpg": {
        "n1": "F#5",
        "n2": "B5",
        "name": "P4"
    },
    "m19000.jpg": {
        "n1": "G5",
        "n2": "G#5",
        "name": "m2"
    },
    "m19002.jpg": {
        "n1": "G5",
        "n2": "B-5",
        "name": "m3"
    },
    "m19004.jpg": {
        "n1": "G5",
        "n2": "C6",
        "name": "P4"
    },
    "m2.jpg": {
        "n1": "C4",
        "n2": "E-4",
        "name": "m3"
    },
    "m2000.jpg": {
        "n1": "D4",
        "n2": "E-4",
        "name": "m2"
    },
    "m20000.jpg": {
        "n1": "G#5",
        "n2": "A5",
        "name": "m2"
    },
    "m20002.jpg": {
        "n1": "G#5",
        "n2": "B5",
        "name": "m3"
    },
    "m2002.jpg": {
        "n1": "D4",
        "n2": "F4",
        "name": "m3"
    },
    "m2004.jpg": {
        "n1": "D4",
        "n2": "G4",
        "name": "P4"
    },
    "m21000.jpg": {
        "n1": "A5",
        "n2": "B-5",
        "name": "m2"
    },
    "m21002.jpg": {
        "n1": "A5",
        "n2": "C6",
        "name": "m3"
    },
    "m22000.jpg": {
        "n1": "B-5",
        "n2": "B5",
        "name": "m2"
    },
    "m23000.jpg": {
        "n1": "B5",
        "n2": "C6",
        "name": "m2"
    },
    "m3000.jpg": {
        "n1": "E-4",
        "n2": "E4",
        "name": "m2"
    },
    "m3002.jpg": {
        "n1": "E-4",
        "n2": "F#4",
        "name": "m3"
    },
    "m3004.jpg": {
        "n1": "E-4",
        "n2": "G#4",
        "name": "P4"
    },
    "m4.jpg": {
        "n1": "C4",
        "n2": "F4",
        "name": "P4"
    },
    "m4000.jpg": {
        "n1": "E4",
        "n2": "F4",
        "name": "m2"
    },
    "m4002.jpg": {
        "n1": "E4",
        "n2": "G4",
        "name": "m3"
    },
    "m4004.jpg": {
        "n1": "E4",
        "n2": "A4",
        "name": "P4"
    },
    "m5000.jpg": {
        "n1": "F4",
        "n2": "F#4",
        "name": "m2"
    },
    "m5002.jpg": {
        "n1": "F4",
        "n2": "G#4",
        "name": "m3"
    },
    "m5004.jpg": {
        "n1": "F4",
        "n2": "B-4",
        "name": "P4"
    },
    "m6000.jpg": {
        "n1": "F#4",
        "n2": "G4",
        "name": "m2"
    },
    "m6002.jpg": {
        "n1": "F#4",
        "n2": "A4",
        "name": "m3"
    },
    "m6004.jpg": {
        "n1": "F#4",
        "n2": "B4",
        "name": "P4"
    },
    "m7000.jpg": {
        "n1": "G4",
        "n2": "G#4",
        "name": "m2"
    },
    "m7002.jpg": {
        "n1": "G4",
        "n2": "B-4",
        "name": "m3"
    },
    "m7004.jpg": {
        "n1": "G4",
        "n2": "C5",
        "name": "P4"
    },
    "m8000.jpg": {
        "n1": "G#4",
        "n2": "A4",
        "name": "m2"
    },
    "m8002.jpg": {
        "n1": "G#4",
        "n2": "B4",
        "name": "m3"
    },
    "m8004.jpg": {
        "n1": "G#4",
        "n2": "C#5",
        "name": "P4"
    },
    "m9000.jpg": {
        "n1": "A4",
        "n2": "B-4",
        "name": "m2"
    },
    "m9002.jpg": {
        "n1": "A4",
        "n2": "C5",
        "name": "m3"
    },
    "m9004.jpg": {
        "n1": "A4",
        "n2": "D5",
        "name": "P4"
    }
}